fleet/GLADE_short.txt
fleet/__init__.py
fleet/catalog.py
fleet/classification_catalog.dat
fleet/classify.py
fleet/model.py
fleet/plot.py
fleet/transient.py
fleet/training_set/table_full_15.txt
fleet/training_set/table_full_20.txt
fleet/training_set/table_full_25.txt
fleet/training_set/table_full_50.txt
fleet/training_set/table_full_65.txt
fleet/training_set/table_full_70.txt
fleet/training_set/table_full_75.txt
fleet/training_set/table_full_90.txt
fleet_pipe-3.0.0.dist-info/LICENSE
fleet_pipe-3.0.0.dist-info/METADATA
fleet_pipe-3.0.0.dist-info/WHEEL
fleet_pipe-3.0.0.dist-info/top_level.txt
fleet_pipe-3.0.0.dist-info/RECORD
