Metadata-Version: 2.1
Name: fleet-pipe
Version: 3.0.0
Summary: Finding Luminous and Exotic Extragalactic Transients
Home-page: https://github.com/gmzsebastian/fleet
Author: ['Sebastian Gomez']
Author-email: sgomez@cfa.harvard.edu
License: MIT
License-File: LICENSE
Requires-Dist: numpy
Requires-Dist: astroquery
Requires-Dist: dustmaps
Requires-Dist: bs4
Requires-Dist: ephem
Requires-Dist: datetime
Requires-Dist: astral ==1.10.1
Requires-Dist: PyAstronomy
Requires-Dist: scikit-learn
Requires-Dist: imbalanced-learn
Requires-Dist: Pillow
Requires-Dist: matplotlib
Requires-Dist: lmfit
Requires-Dist: alerce
Requires-Dist: extinction
Requires-Dist: pandas
Requires-Dist: python-dateutil
Requires-Dist: astropy
Requires-Dist: pathlib
Requires-Dist: requests
Requires-Dist: scipy
Requires-Dist: emcee
Requires-Dist: casjobs
Requires-Dist: mastcasjobs
